tgate/PixArt_Alpha.py
tgate/PixArt_Sigma.py
tgate/SD.py
tgate/SDXL.py
tgate/SDXL_DeepCache.py
tgate/SD_DeepCache.py
tgate/SVD.py
tgate/__init__.py
tgate/tgate_utils.py
tgate-1.0.0.dist-info/LICENSE
tgate-1.0.0.dist-info/METADATA
tgate-1.0.0.dist-info/WHEEL
tgate-1.0.0.dist-info/top_level.txt
tgate-1.0.0.dist-info/RECORD
