Metadata-Version: 2.1
Name: tgate
Version: 1.0.0
Summary: TGATE-V2: Faster Diffusion Through Temporal Attention Decomposition.
Home-page: https://github.com/HaozheLiu-ST/T-GATE/tree/releases/
Author: Wentian Zhang
Author-email: zhangwentianml@gmail.com
Classifier: Programming Language :: Python :: 3
Classifier: License :: OSI Approved :: MIT License
Classifier: Operating System :: OS Independent
Requires-Python: >=3.8.0
License-File: LICENSE
Requires-Dist: diffusers>=0.29.0
Requires-Dist: transformers
Requires-Dist: DeepCache==0.1.1
Requires-Dist: torch
Requires-Dist: accelerate
